main.py
jyrkio_testpypi-2026.1.0.dist-info/METADATA
jyrkio_testpypi-2026.1.0.dist-info/WHEEL
jyrkio_testpypi-2026.1.0.dist-info/top_level.txt
jyrkio_testpypi-2026.1.0.dist-info/RECORD
