Metadata-Version: 2.4
Name: jyrkio_testpypi
Version: 2026.1.0
Summary: Just a test
Author-email: Jyrki Oraskari <jyrki.oraskari@dc.rwth-aachen.de>
Maintainer-email: Jyrki Oraskari <jyrki.oraskari@dc.rwth-aachen.de>
License-Expression: MIT
Project-URL: Homepage, https://example.com
Project-URL: Documentation, https://readthedocs.org
Keywords: test
Classifier: Development Status :: 2 - Pre-Alpha
Requires-Python: >=3.8
